{
  "swagger": "2.0",
  "info": {
    "title": "Cdcs API",
    "version": "1.0"
  },
  "tags": [
    {
      "name": "CdcsService"
    }
  ],
  "schemes": [
    "https"
  ],
  "consumes": [
    "application/json"
  ],
  "produces": [
    "application/json"
  ],
  "paths": {
    "/v1/cdcs/InvokeProcess": {
      "post": {
        "operationId": "CdcsService_InvokeProcess",
        "responses": {
          "200": {
            "description": "A successful response.",
            "schema": {
              "$ref": "#/definitions/v1InvokeProcessResponse"
            }
          },
          "400": {
            "description": "Bad request determined by business logic",
            "schema": {
              "$ref": "#/definitions/v1ExceptionResponse"
            }
          },
          "401": {
            "description": "Authorization failed",
            "schema": {
              "$ref": "#/definitions/v1ExceptionResponse"
            }
          },
          "403": {
            "description": "Permission denied",
            "schema": {
              "$ref": "#/definitions/v1ExceptionResponse"
            }
          },
          "404": {
            "description": "Missing resource",
            "schema": {
              "$ref": "#/definitions/v1ExceptionResponse"
            }
          },
          "405": {
            "description": "Method not allowed",
            "schema": {
              "type": "string",
              "format": "string"
            }
          },
          "500": {
            "description": "Unexpected internal server error",
            "schema": {
              "$ref": "#/definitions/v1ExceptionResponse"
            }
          },
          "503": {
            "description": "Service not available",
            "schema": {
              "$ref": "#/definitions/v1ExceptionResponse"
            }
          },
          "default": {
            "description": "An unexpected error response.",
            "schema": {
              "$ref": "#/definitions/rpcStatus"
            }
          }
        },
        "parameters": [
          {
            "name": "body",
            "in": "body",
            "required": true,
            "schema": {
              "$ref": "#/definitions/v1InvokeProcessRequest"
            }
          }
        ],
        "tags": [
          "Service"
        ]
      }
    },
    "/v1/cdcs/UploadClaimWF1": {
      "post": {
        "operationId": "CdcsService_UploadClaimWF1",
        "responses": {
          "200": {
            "description": "A successful response.",
            "schema": {
              "$ref": "#/definitions/v1UploadClaimWF1Response"
            }
          },
          "400": {
            "description": "Bad request determined by business logic",
            "schema": {
              "$ref": "#/definitions/v1ExceptionResponse"
            }
          },
          "401": {
            "description": "Authorization failed",
            "schema": {
              "$ref": "#/definitions/v1ExceptionResponse"
            }
          },
          "403": {
            "description": "Permission denied",
            "schema": {
              "$ref": "#/definitions/v1ExceptionResponse"
            }
          },
          "404": {
            "description": "Missing resource",
            "schema": {
              "$ref": "#/definitions/v1ExceptionResponse"
            }
          },
          "405": {
            "description": "Method not allowed",
            "schema": {
              "type": "string",
              "format": "string"
            }
          },
          "500": {
            "description": "Unexpected internal server error",
            "schema": {
              "$ref": "#/definitions/v1ExceptionResponse"
            }
          },
          "503": {
            "description": "Service not available",
            "schema": {
              "$ref": "#/definitions/v1ExceptionResponse"
            }
          },
          "default": {
            "description": "An unexpected error response.",
            "schema": {
              "$ref": "#/definitions/rpcStatus"
            }
          }
        },
        "parameters": [
          {
            "name": "body",
            "in": "body",
            "required": true,
            "schema": {
              "$ref": "#/definitions/v1UploadClaimWF1Request"
            }
          }
        ],
        "tags": [
          "Service"
        ]
      }
    },
    "/v1/cdcs/UploadClaimWF2": {
      "post": {
        "operationId": "CdcsService_UploadClaimWF2",
        "responses": {
          "200": {
            "description": "A successful response.",
            "schema": {
              "$ref": "#/definitions/v1UploadClaimWF2Response"
            }
          },
          "400": {
            "description": "Bad request determined by business logic",
            "schema": {
              "$ref": "#/definitions/v1ExceptionResponse"
            }
          },
          "401": {
            "description": "Authorization failed",
            "schema": {
              "$ref": "#/definitions/v1ExceptionResponse"
            }
          },
          "403": {
            "description": "Permission denied",
            "schema": {
              "$ref": "#/definitions/v1ExceptionResponse"
            }
          },
          "404": {
            "description": "Missing resource",
            "schema": {
              "$ref": "#/definitions/v1ExceptionResponse"
            }
          },
          "405": {
            "description": "Method not allowed",
            "schema": {
              "type": "string",
              "format": "string"
            }
          },
          "500": {
            "description": "Unexpected internal server error",
            "schema": {
              "$ref": "#/definitions/v1ExceptionResponse"
            }
          },
          "503": {
            "description": "Service not available",
            "schema": {
              "$ref": "#/definitions/v1ExceptionResponse"
            }
          },
          "default": {
            "description": "An unexpected error response.",
            "schema": {
              "$ref": "#/definitions/rpcStatus"
            }
          }
        },
        "parameters": [
          {
            "name": "body",
            "in": "body",
            "required": true,
            "schema": {
              "$ref": "#/definitions/v1UploadClaimWF2Request"
            }
          }
        ],
        "tags": [
          "Service"
        ]
      }
    },
    "/v1/cdcs/UploadClaimWF3": {
      "post": {
        "operationId": "CdcsService_UploadClaimWF3",
        "responses": {
          "200": {
            "description": "A successful response.",
            "schema": {
              "$ref": "#/definitions/v1UploadClaimWF3Response"
            }
          },
          "400": {
            "description": "Bad request determined by business logic",
            "schema": {
              "$ref": "#/definitions/v1ExceptionResponse"
            }
          },
          "401": {
            "description": "Authorization failed",
            "schema": {
              "$ref": "#/definitions/v1ExceptionResponse"
            }
          },
          "403": {
            "description": "Permission denied",
            "schema": {
              "$ref": "#/definitions/v1ExceptionResponse"
            }
          },
          "404": {
            "description": "Missing resource",
            "schema": {
              "$ref": "#/definitions/v1ExceptionResponse"
            }
          },
          "405": {
            "description": "Method not allowed",
            "schema": {
              "type": "string",
              "format": "string"
            }
          },
          "500": {
            "description": "Unexpected internal server error",
            "schema": {
              "$ref": "#/definitions/v1ExceptionResponse"
            }
          },
          "503": {
            "description": "Service not available",
            "schema": {
              "$ref": "#/definitions/v1ExceptionResponse"
            }
          },
          "default": {
            "description": "An unexpected error response.",
            "schema": {
              "$ref": "#/definitions/rpcStatus"
            }
          }
        },
        "parameters": [
          {
            "name": "body",
            "in": "body",
            "required": true,
            "schema": {
              "$ref": "#/definitions/v1UploadClaimWF3Request"
            }
          }
        ],
        "tags": [
          "Service"
        ]
      }
    },
    "/v1/cdcs/UploadClaimWF4": {
      "post": {
        "operationId": "CdcsService_UploadClaimWF4",
        "responses": {
          "200": {
            "description": "A successful response.",
            "schema": {
              "$ref": "#/definitions/v1UploadClaimWF4Response"
            }
          },
          "400": {
            "description": "Bad request determined by business logic",
            "schema": {
              "$ref": "#/definitions/v1ExceptionResponse"
            }
          },
          "401": {
            "description": "Authorization failed",
            "schema": {
              "$ref": "#/definitions/v1ExceptionResponse"
            }
          },
          "403": {
            "description": "Permission denied",
            "schema": {
              "$ref": "#/definitions/v1ExceptionResponse"
            }
          },
          "404": {
            "description": "Missing resource",
            "schema": {
              "$ref": "#/definitions/v1ExceptionResponse"
            }
          },
          "405": {
            "description": "Method not allowed",
            "schema": {
              "type": "string",
              "format": "string"
            }
          },
          "500": {
            "description": "Unexpected internal server error",
            "schema": {
              "$ref": "#/definitions/v1ExceptionResponse"
            }
          },
          "503": {
            "description": "Service not available",
            "schema": {
              "$ref": "#/definitions/v1ExceptionResponse"
            }
          },
          "default": {
            "description": "An unexpected error response.",
            "schema": {
              "$ref": "#/definitions/rpcStatus"
            }
          }
        },
        "parameters": [
          {
            "name": "body",
            "in": "body",
            "required": true,
            "schema": {
              "$ref": "#/definitions/v1UploadClaimWF4Request"
            }
          }
        ],
        "tags": [
          "Service"
        ]
      }
    },
    "/v1/cdcs/UploadClaimWF5": {
      "post": {
        "operationId": "CdcsService_UploadClaimWF5",
        "responses": {
          "200": {
            "description": "A successful response.",
            "schema": {
              "$ref": "#/definitions/v1UploadClaimWF5Response"
            }
          },
          "400": {
            "description": "Bad request determined by business logic",
            "schema": {
              "$ref": "#/definitions/v1ExceptionResponse"
            }
          },
          "401": {
            "description": "Authorization failed",
            "schema": {
              "$ref": "#/definitions/v1ExceptionResponse"
            }
          },
          "403": {
            "description": "Permission denied",
            "schema": {
              "$ref": "#/definitions/v1ExceptionResponse"
            }
          },
          "404": {
            "description": "Missing resource",
            "schema": {
              "$ref": "#/definitions/v1ExceptionResponse"
            }
          },
          "405": {
            "description": "Method not allowed",
            "schema": {
              "type": "string",
              "format": "string"
            }
          },
          "500": {
            "description": "Unexpected internal server error",
            "schema": {
              "$ref": "#/definitions/v1ExceptionResponse"
            }
          },
          "503": {
            "description": "Service not available",
            "schema": {
              "$ref": "#/definitions/v1ExceptionResponse"
            }
          },
          "default": {
            "description": "An unexpected error response.",
            "schema": {
              "$ref": "#/definitions/rpcStatus"
            }
          }
        },
        "parameters": [
          {
            "name": "body",
            "in": "body",
            "required": true,
            "schema": {
              "$ref": "#/definitions/v1UploadClaimWF5Request"
            }
          }
        ],
        "tags": [
          "Service"
        ]
      }
    },
    "/v1/cdcs/workflows/{workflowName}/claims": {
      "post": {
        "operationId": "CdcsService_UploadClaim",
        "responses": {
          "200": {
            "description": "A successful response.",
            "schema": {
              "$ref": "#/definitions/v1UploadClaimResponse"
            }
          },
          "400": {
            "description": "Bad request determined by business logic",
            "schema": {
              "$ref": "#/definitions/v1ExceptionResponse"
            }
          },
          "401": {
            "description": "Authorization failed",
            "schema": {
              "$ref": "#/definitions/v1ExceptionResponse"
            }
          },
          "403": {
            "description": "Permission denied",
            "schema": {
              "$ref": "#/definitions/v1ExceptionResponse"
            }
          },
          "404": {
            "description": "Missing resource",
            "schema": {
              "$ref": "#/definitions/v1ExceptionResponse"
            }
          },
          "405": {
            "description": "Method not allowed",
            "schema": {
              "type": "string",
              "format": "string"
            }
          },
          "500": {
            "description": "Unexpected internal server error",
            "schema": {
              "$ref": "#/definitions/v1ExceptionResponse"
            }
          },
          "503": {
            "description": "Service not available",
            "schema": {
              "$ref": "#/definitions/v1ExceptionResponse"
            }
          },
          "default": {
            "description": "An unexpected error response.",
            "schema": {
              "$ref": "#/definitions/rpcStatus"
            }
          }
        },
        "parameters": [
          {
            "name": "workflowName",
            "description": "Required: \"wf1\", \"wf2\", \"wf3\", \"wf4\", \"wf5\", or \"process\"",
            "in": "path",
            "required": true,
            "type": "string"
          },
          {
            "name": "body",
            "in": "body",
            "required": true,
            "schema": {
              "$ref": "#/definitions/CdcsServiceUploadClaimBody"
            }
          }
        ],
        "tags": [
          "Service"
        ]
      }
    },
    "/v1/cdcs/workflows/{workflowName}/claims/{claimId}/state": {
      "get": {
        "operationId": "CdcsService_GetClaimState",
        "responses": {
          "200": {
            "description": "A successful response.",
            "schema": {
              "$ref": "#/definitions/v1GetClaimStateResponse"
            }
          },
          "400": {
            "description": "Bad request determined by business logic",
            "schema": {
              "$ref": "#/definitions/v1ExceptionResponse"
            }
          },
          "401": {
            "description": "Authorization failed",
            "schema": {
              "$ref": "#/definitions/v1ExceptionResponse"
            }
          },
          "403": {
            "description": "Permission denied",
            "schema": {
              "$ref": "#/definitions/v1ExceptionResponse"
            }
          },
          "404": {
            "description": "Missing resource",
            "schema": {
              "$ref": "#/definitions/v1ExceptionResponse"
            }
          },
          "405": {
            "description": "Method not allowed",
            "schema": {
              "type": "string",
              "format": "string"
            }
          },
          "500": {
            "description": "Unexpected internal server error",
            "schema": {
              "$ref": "#/definitions/v1ExceptionResponse"
            }
          },
          "503": {
            "description": "Service not available",
            "schema": {
              "$ref": "#/definitions/v1ExceptionResponse"
            }
          },
          "default": {
            "description": "An unexpected error response.",
            "schema": {
              "$ref": "#/definitions/rpcStatus"
            }
          }
        },
        "parameters": [
          {
            "name": "workflowName",
            "description": "Required: \"wf1\", \"wf2\", \"wf3\", \"wf4\", \"wf5\", or \"process\"\nUsed to select which workflow manager to query.",
            "in": "path",
            "required": true,
            "type": "string"
          },
          {
            "name": "claimId",
            "description": "Required: Unique identifier of the claim",
            "in": "path",
            "required": true,
            "type": "string"
          }
        ],
        "tags": [
          "Service"
        ]
      }
    }
  },
  "definitions": {
    "CdcsServiceUploadClaimBody": {
      "type": "object",
      "properties": {
        "policyId": {
          "type": "string",
          "title": "Common fields (used by multiple workflows)"
        },
        "claimId": {
          "type": "string",
          "title": "Used by WF3, WF4, WF5"
        },
        "guidewireClaimId": {
          "type": "string",
          "title": "WF2 fields"
        },
        "gwClaimId": {
          "type": "string",
          "title": "Alternative to guidewire_claim_id"
        },
        "invoiceAmount": {
          "type": "string",
          "title": "WF3 fields"
        },
        "signerName": {
          "type": "string"
        },
        "signerEmail": {
          "type": "string"
        },
        "originatorName": {
          "type": "string"
        },
        "recipientName": {
          "type": "string"
        },
        "issueDate": {
          "type": "string",
          "title": "YYYY-MM-DD"
        },
        "customerId": {
          "type": "string",
          "title": "WF4 fields"
        },
        "referenceNumber": {
          "type": "string"
        },
        "dueDate": {
          "type": "string",
          "title": "YYYY-MM-DD"
        },
        "isInclusiveTax": {
          "type": "boolean"
        },
        "lineItems": {
          "type": "array",
          "items": {
            "type": "object",
            "$ref": "#/definitions/v1LineItem"
          }
        },
        "currencyCode": {
          "type": "string"
        }
      },
      "description": "Unified request for uploading a claim to any workflow.\nThe server routes by workflow_name to the corresponding workflow manager."
    },
    "protobufAny": {
      "type": "object",
      "properties": {
        "@type": {
          "type": "string"
        }
      },
      "additionalProperties": {}
    },
    "rpcStatus": {
      "type": "object",
      "properties": {
        "code": {
          "type": "integer",
          "format": "int32"
        },
        "message": {
          "type": "string"
        },
        "details": {
          "type": "array",
          "items": {
            "type": "object",
            "$ref": "#/definitions/protobufAny"
          }
        }
      }
    },
    "v1Exception": {
      "type": "object",
      "properties": {
        "id": {
          "type": "string",
          "description": "UUID for exception."
        },
        "type": {
          "$ref": "#/definitions/v1ExceptionType",
          "description": "Type of exception."
        },
        "timestamp": {
          "type": "string",
          "description": "Timestamp for when the exception occurred (RFC3339)."
        },
        "description": {
          "type": "string",
          "description": "Human readable description of exception."
        },
        "exceptionMetadata": {
          "type": "object",
          "additionalProperties": {
            "type": "string"
          },
          "description": "Additional metadata about the exception."
        }
      },
      "description": "General message for exceptions."
    },
    "v1ExceptionResponse": {
      "type": "object",
      "properties": {
        "exception": {
          "$ref": "#/definitions/v1Exception",
          "description": "An exception if an error occurred during processing request."
        }
      },
      "description": "Exception messages."
    },
    "v1ExceptionType": {
      "type": "string",
      "enum": [
        "INVALID_TYPE",
        "BUSINESS",
        "SERVICE_NOT_AVAILABLE",
        "INFRASTRUCTURE",
        "UNEXPECTED",
        "SECURITY_VIOLATION"
      ],
      "default": "INVALID_TYPE",
      "description": "Type of exception.\n\n - INVALID_TYPE: Default for no exception.\n - BUSINESS: Business logic error.\n - SERVICE_NOT_AVAILABLE: A service was unavailable.\n - INFRASTRUCTURE: Infrastructure was down.\n - UNEXPECTED: Catch-all for all other types.\n - SECURITY_VIOLATION: Security related error."
    },
    "v1GetClaimStateResponse": {
      "type": "object",
      "properties": {
        "claimId": {
          "type": "string"
        },
        "state": {
          "type": "string"
        },
        "exception": {
          "$ref": "#/definitions/v1Exception"
        }
      }
    },
    "v1InvokeProcessRequest": {
      "type": "object",
      "properties": {
        "policyId": {
          "type": "string",
          "title": "Required"
        },
        "guidewireClaimId": {
          "type": "string",
          "title": "Optional"
        },
        "gwClaimId": {
          "type": "string",
          "title": "Optional"
        },
        "signerEmail": {
          "type": "string",
          "title": "Optional"
        },
        "signerName": {
          "type": "string",
          "title": "Optional"
        },
        "invoiceAmount": {
          "type": "string",
          "title": "Optional"
        },
        "originatorName": {
          "type": "string",
          "title": "Optional"
        },
        "recipientName": {
          "type": "string",
          "title": "Optional"
        },
        "issueDate": {
          "type": "string",
          "title": "Optional (YYYY-MM-DD)"
        }
      }
    },
    "v1InvokeProcessResponse": {
      "type": "object",
      "properties": {
        "claimId": {
          "type": "string"
        },
        "state": {
          "type": "string"
        },
        "exception": {
          "$ref": "#/definitions/v1Exception"
        }
      }
    },
    "v1LineItem": {
      "type": "object",
      "properties": {
        "name": {
          "type": "string"
        },
        "rate": {
          "type": "number",
          "format": "double"
        },
        "quantity": {
          "type": "integer",
          "format": "int32"
        }
      },
      "title": "Line item for Zoho invoice"
    },
    "v1UploadClaimResponse": {
      "type": "object",
      "properties": {
        "claimId": {
          "type": "string"
        },
        "state": {
          "type": "string"
        },
        "exception": {
          "$ref": "#/definitions/v1Exception"
        }
      }
    },
    "v1UploadClaimWF1Request": {
      "type": "object",
      "properties": {
        "policyId": {
          "type": "string"
        }
      }
    },
    "v1UploadClaimWF1Response": {
      "type": "object",
      "properties": {
        "claimId": {
          "type": "string"
        },
        "state": {
          "type": "string"
        },
        "exception": {
          "$ref": "#/definitions/v1Exception"
        }
      }
    },
    "v1UploadClaimWF2Request": {
      "type": "object",
      "properties": {
        "policyId": {
          "type": "string"
        },
        "guidewireClaimId": {
          "type": "string"
        }
      }
    },
    "v1UploadClaimWF2Response": {
      "type": "object",
      "properties": {
        "claimId": {
          "type": "string"
        },
        "state": {
          "type": "string"
        },
        "exception": {
          "$ref": "#/definitions/v1Exception"
        }
      }
    },
    "v1UploadClaimWF3Request": {
      "type": "object",
      "properties": {
        "claimId": {
          "type": "string"
        },
        "invoiceAmount": {
          "type": "string",
          "title": "or double"
        },
        "signerName": {
          "type": "string"
        },
        "signerEmail": {
          "type": "string"
        },
        "originatorName": {
          "type": "string",
          "title": "optional"
        },
        "recipientName": {
          "type": "string",
          "title": "optional"
        },
        "issueDate": {
          "type": "string",
          "title": "YYYY-MM-DD"
        }
      }
    },
    "v1UploadClaimWF3Response": {
      "type": "object",
      "properties": {
        "claimId": {
          "type": "string"
        },
        "state": {
          "type": "string"
        },
        "exception": {
          "$ref": "#/definitions/v1Exception"
        }
      }
    },
    "v1UploadClaimWF4Request": {
      "type": "object",
      "properties": {
        "policyId": {
          "type": "string",
          "title": "Optional: defaults to \"POL-8872\" if not provided"
        },
        "customerId": {
          "type": "string",
          "description": "Required: Zoho customer ID",
          "title": "Zoho invoice fields"
        },
        "referenceNumber": {
          "type": "string",
          "title": "Required: Claim reference number (used as claim_id if claim_id not provided)"
        },
        "dueDate": {
          "type": "string",
          "title": "Required: Invoice due date (YYYY-MM-DD)"
        },
        "isInclusiveTax": {
          "type": "boolean",
          "title": "Required: Whether tax is inclusive"
        },
        "lineItems": {
          "type": "array",
          "items": {
            "type": "object",
            "$ref": "#/definitions/v1LineItem"
          },
          "title": "Required: Invoice line items"
        },
        "claimId": {
          "type": "string",
          "description": "Optional: Override claim_id (defaults to reference_number)",
          "title": "Optional overrides"
        },
        "currencyCode": {
          "type": "string",
          "title": "Optional: Currency code (defaults to \"GBP\")"
        }
      }
    },
    "v1UploadClaimWF4Response": {
      "type": "object",
      "properties": {
        "claimId": {
          "type": "string"
        },
        "state": {
          "type": "string"
        },
        "exception": {
          "$ref": "#/definitions/v1Exception"
        }
      }
    },
    "v1UploadClaimWF5Request": {
      "type": "object",
      "properties": {
        "policyId": {
          "type": "string"
        }
      }
    },
    "v1UploadClaimWF5Response": {
      "type": "object",
      "properties": {
        "claimId": {
          "type": "string"
        },
        "state": {
          "type": "string"
        },
        "exception": {
          "$ref": "#/definitions/v1Exception"
        }
      }
    }
  },
  "securityDefinitions": {
    "X-API-KEY": {
      "type": "apiKey",
      "name": "X-API-KEY",
      "in": "header"
    }
  }
}
